ab_versions/__init__.py
ab_versions/ab_versions.pypy38-pp73-s390x-linux-gnu.so
ab_versions_py-0.10.1.dist-info/METADATA
ab_versions_py-0.10.1.dist-info/WHEEL
ab_versions_py-0.10.1.dist-info/RECORD
