Metadata-Version: 2.4
Name: ab_versions_py
Version: 0.10.1
